Workbook

Sheet Instructions
A1: ECONOMICS OF BANKING - GROUP ASSIGNMENT
A2: Silicon Valley Bank: A Risk Analysis Case Study
A3: University of Groningen - Academic Year 2025/2026
A5: Color Legend:
A6: YELLOW cells = Data you extract from the UBPR report (input cells)
A7: GREEN cells = Cells where you enter a formula or calculated value
A8: GRAY cells = Given parameters. Do not overwrite!
A10: All dollar amounts are in thousands ($000s) as in the UBPR.
A11: For each extracted data point, record the UBPR page number in the Data Extraction sheet
A13: Sheets:
A14: 1. Instructions
A15: 2. Data Extraction: Key items from the UBPR
... A23: TEAM INFORMATION:
A25: Team Number: | B25: 66
A26: Team Members: | B26: Oleksandr Kravets, Tanner Weight, Aleksander Bartkiewicz, Sven van den Boomen, Youssef Abulkassem
A27: Stress Scenario (A-H): | B27: F
A28: Comparison Bank: | B28: The Bank of New York Mellon

Sheet Data Extraction
A1: PART 1: DATA EXTRACTION FROM SVB UBPR (12/31/2022)
A2: A. Balance Sheet Items
A3: Item | B3: SVB ($000s) | C3: Prior Year ($000s) | D3: UBPR Page
A4: Assets:
A5: Net Loans & Leases: | B5: 73613000 | C5: 65852000 | D5: Pg 4 | E5: Fill the rest for each YELLOW cell
A6: Commercial Loans | B6: 19094000 | C6: 16070000 | D6: Pg 4
A7: ACL on LN&LS HFI | B7: 636000 | C7: 423000 | D7: Pg 4
A8: Net Securities: | B8: 117297000 | C8: 125288000 | D8: Pg 4
A9: U.S. Treasury & Agency Securities | B9: 92156000 | C9: 100862000 | D9: Pg 4
A10: Interest-Bearing Bank Balances | B10: 11319000 | C10: 11085000 | D10: Pg 4
A11: Total Earning Assets | B11: 203063000 | C11: 202965000 | D11: Pg 4
A12: Other Real Estate Owned | B12: 0 | C12: 1000 | D12: Pg 4
A13: Total Assets | B13: 209026000 | C13: 208581000 | D13: Pg 4
A15: Liabilities:
A16: Total Deposits: | B16: 175378000 | C16: 191431000 | D16: Pg 4
A17: Demand Deposits | B17: 10432000 | C17: 7231000 | D17: Pg 4
A18: All Now & ATS Accounts | B18: 55000 | C18: 68000 | D18: Pg 4
A19: Money Market Deposit Accounts | B19: 149444000 | C19: 163723000 | D19: Pg 4
A20: Other Savings Deposits | B20: 79000 | C20: 3978000 | D20: Pg 4
A21: Time Deps at or Below Insurance Limit | B21: 65000 | C21: 96000 | D21: Pg 4
A22: Time Deps Above Insurance Limit | B22: 1404000 | C22: 282000 | D22: Pg 4
A23: Deposits in Foreign Offices | B23: 13899000 | C23: 16053000 | D23: Pg 4
A24: Total Liabilities | B24: 193570000 | C24: 193786000 | D24: Pg 4
A25: Total Bank Capital & Min Int | B25: 15456000 | C25: 14795000 | D25: Pg 4
A26: Total Liabilities & Capital | B26: 209026000 | C26: 208581000 | D26: Pg 4
A28: Memoranda:
A29: Total Intangibles (Memo) | B29: 285000 | C29: 298000 | D29: Pg 11
A30: Available-for-Sale Securities (Memo) | B30: 25976000 | C30: 27093000 | D30: Pg 4
A31: Held-to-Maturity Securities (Memo)+ | B31: 91327000 | C31: 98201000 | D31: Pg 4
A32: Non-Interest Bearing Deposits (Memo) | B32: 83020000 | C32: 128079000 | D32: Pg 4
A33: Estimate of Uninsured Deposits (Memo) | B33: 151592000 | C33: 166017000 | D33: Pg 4
A35: B. Income Statement & Yield Items
A36: Item | B36: SVB | C36: Prior Year | D36: UBPR Page
A37: Net Interest Income (TE) ($000s) | B37: 4611646 | C37: 3253646 | D37: Pg 2
A38: Net Income ($000s) | B38: 2024000 | C38: 1294000 | D38: Pg 2
A40: Margin analysis:
A41: Int Inc (TE) to Avg Earn Assets (%) | B41: 2.72 | C41: 2.08 | D41: Pg 1
A42: Int Expense to Avg Earn Assets (%) | B42: 0.52 | C42: 0.04 | D42: Pg 1
A43: Net Int Inc (TE) to Avg Earn Assets (%) | B43: 2.2 | C43: 2.05 | D43: Pg 1
A45: Yield on or cost of:
A46: Yield: Commercial & Industrial Loans (%) | B46: 6.66 | C46: 5.75 | D46: Pg 3A
A47: Yield: Total Investment Securities TE (%) | B47: 1.84 | C47: 1.59 | D47: Pg 3A
A48: Yield: US Treas & Agency excl MBS (%) | B48: 1.34 | C48: 1.34 | D48: Pg 3A
A49: Cost: All Interest-Bearing Funds (%) | B49: 0.6 | C49: 0.04 | D49: Pg 3A
A51: C. Interest Rate Risk Data
A52: Item (% of Total Assets) | B52: SVB (%) | C52: Peer Group 1 (%) | D52: SVB PCT | E52: Prior Year (%) | F52: UBPR Page
A53: Short-Term Assets to Total Assets (Up to 1 Yr) | B53: 35.67 | C53: 42.85 | D53: 25 | E53: 32.14 | F53: Pg 9
A54: Med-Term Assets to Total Assets (>1-5 Yrs) | B54: 9.74 | C54: 14.3 | D54: 21 | E54: 10.01 | F54: Pg 9
A55: Long-Term Assets to Total Assets (> 5 Yrs) | B55: 51.92 | C55: 32.2 | D55: 90 | E55: 55.26 | F55: Pg 9
A56: Short-Term Liabilities to Total Assets (Up to 1 Yr) | B56: 84.69 | C56: 79.72 | D56: 68 | E56: 84.13 | F56: Pg 9
A57: Med-Term Liabilities to Total Assets (>1-5 Yrs) | B57: 0 | C57: 2.43 | D57: 9 | E57: 0.01 | F57: Pg 9
A58: Long-Term Liabilities to Total Assets (> 5 Yrs) | B58: 0 | C58: 0.36 | D58: 18 | E58: 0 | F58: Pg 9
A60: D. Unrealized Gains/Losses
A61: Item (% of Tier 1 Cap) | B61: SVB (%) | C61: Peer Group 1 (%) | D61: SVB PCT | E61: Prior Year (%) | F61: UBPR Page
A62: AFS Sec Unrl App (Dep) to Tier 1 Cap (%) | B62: -14.86 | C62: -15.48 | D62: 50 | E62: -1.01 | F62: Pg 9A
A63: HTM Sec Unrl App (Dep) to Tier 1 Cap (%) | B63: -89.2 | C63: -16.77 | D63: 3 | E63: -7.67 | F63: Pg 9A
A64: AFS/HTM Unrl App (Dep) to Tier 1 Cap (%) | B64: -104.06 | C64: -31.99 | D64: 3 | E64: -0.9 | F64: Pg 9A
A66: E. Liquidity Risk Data
A67: Item | B67: SVB (%) | C67: Peer Group 1 (%) | D67: SVB PCT | E67: Prior Year (%) | F67: UBPR Page
A68: Net Non Core Fund Dep New $250M (%) | B68: 9.34 | C68: 1.36 | D68: 71 | E68: 2.29 | F68: Pg 1
A69: Net Loans & Leases to Deposits (%) | B69: 41.97 | C69: 61.72 | D69: 18 | E69: 34.4 | F69: Pg 1
A70: Liquid Assets FV to Total Assets (%) | B70: 55.19 | C70: 37.99 | D70: 84 | E70: 66.18 | F70: Pg 10
A71: Cash & Due From Banks (%) | B71: 0.57 | C71: 0.81 | D71: 34 | E71: 0.98 | F71: Pg 10
A72: Interest-Bearing Bank Balances (%) | B72: 5.42 | C72: 10.69 | D72: 37 | E72: 5.31 | F72: Pg 10
A73: AFS Sec Fair Value (%) | B73: 12.43 | C73: 13.99 | D73: 43 | E73: 12.99 | F73: Pg 10
A74: HTM Sec Fair Value (%) | B74: 36.44 | C74: 9.16 | D74: 93 | E74: 46.61 | F74: Pg 10
A75: Fed Funds Sold & Resales (%) | B75: 0.34 | C75: 1.46 | D75: 59 | E75: 0.29 | F75: Pg 10
A76: Non-retirement Dep > $250M to Total Assets (%) | B76: 74.99 | C76: 45.87 | D76: 93 | E76: 81.93 | F76: Pg 10
A77: Wholesale Funding to Total Assets (%) | B77: 14.1 | C77: 14.63 | D77: 65 | E77: 7.75 | F77: Pg 10
A79: F. Loan Mix & Credit Risk Data
A80: Item | B80: SVB | C80: Peer Group 1 | D80: SVB PCT | E80: Prior Year | F80: UBPR Page
A81: Loan Mix:
A82: Real Estate Loans to Average Gross LN&LS (%) | B82: 17.02 | C82: 36.28 | D82: 15 | E82: 13.82 | F82: Pg 7A
A83: Commercial & Industrial Loans to Average Gross LN&LS (%) | B83: 25.01 | C83: 22.91 | D83: 59 | E83: 28.1 | F83: Pg 7A
A84: Loans to Individuals to Average Gross LN&LS (%) | B84: 0.71 | C84: 14.78 | D84: 12 | E84: 0.72 | F84: Pg 7A
A85: Non-Depository and Other to Average Gross LN&LS (%) | B85: 56.17 | C85: 18.84 | D85: 87 | E85: 56.83 | F85: Pg 7A
A86: Foreign Office Loans & Leases to Average Gross LN&LS (%) | B86: 10.03 | C86: 2.68 | D86: 81 | E86: 10.3 | F86: Pg 7A
A88: Credit risk:
A89: Net Loss to Avg Total LN&LS (%) | B89: 0.1 | C89: 0.24 | D89: 37 | E89: 0.21 | F89: Pg 1
A90: ACL on LN&LS HFI to LN&LS HFI (%) | B90: 0.86 | C90: 1.24 | D90: 34 | E90: 0.64 | F90: Pg 1
A91: ACL on LN&LS HFI to Nonaccrual LN&LS (X) | B91: 4.78 | C91: 3.49 | D91: 80 | E91: 5.04 | F91: Pg 1
A92: Earnings Coverage of Net Losses (X) | B92: 42.15 | C92: 103.38 | D92: 75 | E92: 15.65 | F92: Pg 1
A93: Non-Curr Lns+OREO to Lns+OREO (%) | B93: 0.19 | C93: 0.61 | D93: 21 | E93: 0.13 | F93: Pg 1
A94: 30-89 Days Past Due (%) | B94: 0.14 | C94: 0.49 | D94: 25 | E94: 0.11 | F94: Pg 1
A95: Total LN&LS 90+ Days PD & Nonaccrual (%) | B95: 0.19 | C95: 0.6 | D95: 21 | E95: 0.13 | F95: Pg 1
A96: Total Non-Current LN&LS ($000s) | B96: 139000 | E96: 84000 | F96: Pg 8
A98: G. Capital Adequacy Data
A99: Item | B99: SVB | C99: Peer Group 1 | D99: SVB PCT | E99: Prior Year | F99: UBPR Page
A100: Leverage Ratio (%) | B100: 7.9626 | C100: 8.76 | D100: 21 | E100: 7.2429 | F100: Pg 11
A101: Com Equity Tier 1 Cap Ratio (%) | B101: 15.2639 | C101: 14.31 | D101: 65 | E101: 14.8879 | F101: Pg 11
A102: Tier 1 Capital Ratio (%) | B102: 15.26 | C102: 14.48 | D102: 62 | E102: 14.8879 | F102: Pg 11
A103: Total Capital Ratio (%) | B103: 16.0507 | C103: 15.78 | D103: 62 | E103: 15.4041 | F103: Pg 11
A104: Bank Eq Cap + Min Int to Assets (%) | B104: 7.39 | C104: 9.08 | D104: 18 | E104: 7.09 | F104: Pg 11
A105: Tier 1 Capital ($000s) | B105: 16995000 | E105: 14622000 | F105: Pg 11A
A106: 20% Category (On-BS) ($000s) | B106: 15750200 | E106: 17303400 | F106: Pg 11B
A107: 50% Category (On-BS) ($000s) | B107: 4666500 | E107: 3937000 | F107: Pg 11B
A108: 100% Category (On-BS) ($000s) | B108: 68948000 | E108: 61084000 | F108: Pg 11B
A109: 150% Category (On-BS) ($000s) | B109: 10500 | E109: 54000 | F109: Pg 11B
A110: Other On-BS Categories ($000s) | B110: 23000 | E110: 34000 | F110: Pg 11B
A111: On-Balance Sheet RWA Subtotal ($000s) | B111: 89598200 | E111: 53952000 | F111: Pg 11B
...

Sheet Interest Rate Risk
A1: PART 2A: INTEREST RATE RISK ANALYSIS
A3: Q1. REPRICING GAP MODEL
A4: Use the maturity/repricing bucket data you have extracted in the Data Extraction sheet. Convert each share into dollars. Compute the Gap for each bucket and the Cumulative Gap across buckets.
A6: Total Assets ($000s) [from Data Extraction]: | B6: ='Data Extraction'!B13 -> 209026000
A8: Maturity Bucket | B8: RSA (% of Assets) | C8: RSA ($000s) | D8: RSL (% of Assets) | E8: RSL ($000s) | F8: GAP ($000s) | G8: Cum. GAP ($000s)
A9: Up to 1 Year | B9: ='Data Extraction'!B53 -> 35.67 | C9: =B6*(B9/100) -> 74559574 | D9: ='Data Extraction'!B56 -> 84.69 | E9: =B6*(D9/100) -> 1.7702412e+08 | F9: =C9-E9 -> -1.0246455e+08 | G9: =F9 -> -1.0246455e+08
A10: > 1 Year to 5 Years | B10: ='Data Extraction'!B54 -> 9.74 | C10: =B6*(B10/100) -> 20359132 | D10: ='Data Extraction'!B57 -> 0 | E10: =B6*D10 -> 0 | F10: =C10-E10 -> 20359132 | G10: =G9+F10 -> -82105413
A11: > 5 Years | B11: ='Data Extraction'!B55 -> 51.92 | C11: =B6*(B11/100) -> 1.085263e+08 | D11: ='Data Extraction'!B58 -> 0 | E11: =B6*D11 -> 0 | F11: =C11-E11 -> 1.085263e+08 | G11: =G10+F11 -> 26420886
A12: TOTAL | B12: =SUM(B9:B11) -> 97.33 | C12: =B12*(B6/100) -> 2.0344501e+08 | D12: =SUM(D9:D11) -> 84.69 | E12: =SUM(E9:E11) -> 1.7702412e+08 | F12: =C12-E12 -> 26420886
A15: Q2. NET INTEREST INCOME (NII) SENSITIVITY
A16: Using the 1-year Cumulative Gap from Q1, calculate the change in SVB's Net Interest Income under the following scenarios:
A17: a) Equal rate changes: +100 bps, +200 bps
A18: Scenario | B18: Cum. 1-Yr GAP ($000s) | C18: ΔR (decimal) | D18: ΔNII ($000s)
A19: Equal: +100 bps | B19: =G9 -> -1.0246455e+08 | C19: 0.01 | D19: =B19*C19 -> -1024645.5
A20: Equal: +200 bps | B20: =G9 -> -1.0246455e+08 | C20: 0.02 | D20: =B20*C20 -> -2049290.9
A22: b) Unequal rate change: assume RSA rates rise by +150 bps while RSL rates rise by +75 bps. ΔNII = (RSA × ΔRRSA) − (RSL × ΔRRSL)
A23: Item | B23: Value
A24: RSA Up to 1 Year ($000s) | B24: =C9 -> 74559574
A25: ΔRRSA (decimal) | B25: 0.015
A26: RSL Up to 1 Year ($000s) | B26: =E9 -> 1.7702412e+08
A27: ΔRRSL (decimal) | B27: 0.0075
A28: Interest Revenue Change = RSA × ΔRRSA ($000s) | B28: =B24*B25 -> 1118393.6
A29: Interest Expense Change = RSL × ΔRRSL ($000s) | B29: =B26*B27 -> 1327680.9
A30: ΔNII ($000s) | B30: =B28-B29 -> -209287.28
A33: Q3. UNREALIZED GAINS/LOSSES ON SECURITIES
A34: Compute the dollar amount of unrealized losses.
A35: Item | B35: 12/31/2022 | C35: 12/31/2021 | D35: Change
A36: AFS Sec Unrl App (Dep) to Tier 1 Cap (%) | B36: ='Data Extraction'!B62 -> -14.86 | C36: ='Data Extraction'!E62 -> -1.01 | D36: =B36-C36 -> -13.85
A37: HTM Sec Unrl App (Dep) to Tier 1 Cap (%) | B37: ='Data Extraction'!B63 -> -89.2 | C37: ='Data Extraction'!E63 -> -7.67 | D37: =B37-C37 -> -81.53
A38: Total AFS/HTM Unrl App (Dep) to Tier 1 Cap (%) | B38: ='Data Extraction'!B64 -> -104.06 | C38: ='Data Extraction'!E64 -> -0.9 | D38: =B38-C38 -> -103.16
A39: Tier 1 Capital ($000s) | B39: ='Data Extraction'!B105 -> 16995000 | C39: ='Data Extraction'!E105 -> 14622000 | D39: =B39-C39 -> 2373000
A40: Estimated $ Unrealized Loss AFS | B40: =B36/100*$B$39 -> -2525457 | C40: =C36/100*$C$39 -> -147682.2 | D40: =B40-C40 -> -2377774.8
A41: Estimated $ Unrealized Loss HTM | B41: =B37/100*$B$39 -> -15159540 | C41: =C37/100*$C$39 -> -1121507.4 | D41: =B41-C41 -> -14038033
A42: Estimated $ Unrealized Loss AFS+HTM ($000s) | B42: =B38/100*$B$39 -> -17684997 | C42: =C38/100*$C$39 -> -131598 | D42: =B42-C42 -> -17553399
A45: Q4. DURATION GAP ANALYSIS
A46: Compute the change in the market value of SVB's equity (ΔE) under a +200 bps parallel shock
A47: Parameter | B47: Value | C47: Source
A48: DA (Weighted-Avg Duration of Assets) | B48: 7.43 | C48: Given
A49: DL (Weighted-Avg Duration of Liabilities) | B49: 1.12 | C49: Given
A50: k = Total Liabilities / Total Assets | B50: ='Data Extraction'!B24/'Data Extraction'!B13 -> 0.92605705 | C50: Calculate from Data Extraction
A51: A = Total Assets ($000s) | B51: ='Data Extraction'!B13 -> 209026000 | C51: Data Extraction
A52: R = Net Int Inc (TE) to Avg Earn Assets (decimal) | B52: ='Data Extraction'!B43/100 -> 0.022 | C52: Data Extraction. Convert % to decimal
A53: Duration Gap | B53: =B48-(B50*B49) -> 6.3928161 | C53: Calculate
A55: Interest rate increase: 200 basis points | B55: 0.02 | C55: Given
A56: ΔE ($000s) | B56: =-B53*B51*(B55/(1+B52)) -> -26149996 | C56: Calculate

Sheet Liquidity Risk
A1: PART 2B: LIQUIDITY RISK ANALYSIS
A3: Q5. DEPOSIT STRUCTURE
A5: Total Deposits ($000s) [from Data Extraction]: | B5: ='Data Extraction'!B16 -> 175378000
A6: Total Assets ($000s) [from Data Extraction]: | B6: ='Data Extraction'!B13 -> 209026000
A8: Deposit Category | B8: Value ($000s) | C8: % of Total Deposits | D8: % of Total Assets
A9: Demand Deposits | B9: ='Data Extraction'!B17 -> 10432000 | C9: =B9/$B$5*100 -> 5.9482945 | D9: =B9/$B$6*100 -> 4.9907667
A10: All now & ATS Accounts | B10: ='Data Extraction'!B18 -> 55000 | C10: =B10/$B$5*100 -> 0.031360832 | D10: =B10/$B$6*100 -> 0.026312516
A11: Money Market Deposit Accounts | B11: ='Data Extraction'!B19 -> 149444000 | C11: =B11/$B$5*100 -> 85.212512 | D11: =B11/$B$6*100 -> 71.495412
A12: Other Savings Deposits | B12: ='Data Extraction'!B20 -> 79000 | C12: =B12/$B$5*100 -> 0.045045559 | D12: =B12/$B$6*100 -> 0.037794341
A13: Time Deps at or Below Insurance Limit | B13: ='Data Extraction'!B21 -> 65000 | C13: =B13/$B$5*100 -> 0.037062801 | D13: =B13/$B$6*100 -> 0.03109661
A14: Time Deps Above Insurance Limit | B14: ='Data Extraction'!B22 -> 1404000 | C14: =B14/$B$5*100 -> 0.80055651 | D14: =B14/$B$6*100 -> 0.67168678
A15: Deposits in Foreign Offices | B15: ='Data Extraction'!B23 -> 13899000 | C15: =B15/$B$5*100 -> 7.9251674 | D15: =B15/$B$6*100 -> 6.649412
A17: Memo: Estimate of Uninsured Deposits | B17: ='Data Extraction'!B33 -> 151592000 | C17: =B17/$B$5*100 -> 86.437295 | D17: =B17/$B$6*100 -> 72.523035
A18: Insured Deposits | B18: =B5-B17 -> 23786000 | C18: =B18/$B$5*100 -> 13.562705 | D18: =B18/$B$6*100 -> 11.379446
A19: Memo: Non-Interest Bearing Deposits | B19: ='Data Extraction'!B32 -> 83020000 | C19: =B19/$B$5*100 -> 47.33775 | D19: =B19/$B$6*100 -> 39.717547
A21: Q6. LIQUIDITY RATIOS AND INDICATORS
A22: a) State whether SVB's liquidity position is favorable, unfavorable, or neutral relative to the peer group.
A23: Ratio | B23: SVB | C23: Peer Group 1 | D23: Favorable, Unfavorable, or Neutral relative to PG?
A24: Net Non Core Fund Dep New $250M (%) | B24: ='Data Extraction'!B68 -> 9.34 | C24: ='Data Extraction'!C68 -> 1.36 | D24: Unfavorable - SVB higher than PG (more reliance on non-core funding)
A25: Net Loans & Leases to Deposits (%) | B25: ='Data Extraction'!B69 -> 41.97 | C25: ='Data Extraction'!C69 -> 61.72 | D25: Favorable - SVB lower than PG (less loan-to-deposit pressure)
A26: Liquid Assets FV to Total Assets (%) | B26: ='Data Extraction'!B70 -> 55.19 | C26: ='Data Extraction'!C70 -> 37.99 | D26: Favorable - SVB higher than PG (more liquid assets)
A27: Non-retirement Dep > $250M to Total Assets (%) | B27: ='Data Extraction'!B76 -> 74.99 | C27: ='Data Extraction'!C76 -> 45.87 | D27: Unfavorable - SVB higher than PG (more uninsured large deposits at risk)
A28: Wholesale Funding to Total Assets (%) | B28: ='Data Extraction'!B77 -> 14.1 | C28: ='Data Extraction'!C77 -> 14.63 | D28: Neutral - SVB slightly below PG
A30: b) Compute SVB's liquid assets by component using the data from the Data Extraction sheet.
A31: Then compute (i) cash-like assets (Cash + Interest-Bearing Bank Balances + Fed Funds Sold), and (ii) cash-like assets plus AFS securities.
A32: These values are used in the Stress Scenario (Q15-Q16)
A33: Item | B33: Value ($000s)
A34: Liquid Assets FV in $ ($000s) | B34: =B26/100*B6 -> 1.1536145e+08
A35: Cash & Due From Banks $ ($000s) | B35: ='Data Extraction'!B71/100*$B$6 -> 1191448.2
A36: Interest-Bearing Bank Balances $ ($000s) | B36: ='Data Extraction'!B72/100*$B$6 -> 11329209
A37: AFS Sec Fair Value $ ($000s) | B37: ='Data Extraction'!B73/100*$B$6 -> 25981932
A38: HTM Sec Fair Value $ ($000s) | B38: ='Data Extraction'!B74/100*$B$6 -> 76169074
A39: Fed Funds Sold & Resales $ ($000s) | B39: ='Data Extraction'!B75/100*$B$6 -> 710688.4
A40: Cash-like Assets in $ ($000s) = Cash + IBBB + Fed Funds Sold | B40: =B35+B36+B39 -> 13231346
A41: Cash-like Assets + AFS Sec $ ($000s) | B41: =B40+B37 -> 39213278

Sheet Credit Risk
A1: PART 2C: CREDIT RISK ANALYSIS
A3: Q7. LOAN PORTFOLIO COMPOSITION
A4: Loan Category (% of Avg Gross LN&LS) | B4: SVB (%) | C4: Peer Group 1 (%) | D4: Difference (pp)
A5: Real Estate Loans | B5: 17.02 | C5: 36.28 | D5: =B5-C5 -> -19.26
A6: Commercial & Industrial Loans | B6: 25.01 | C6: 22.91 | D6: =B6-C6 -> 2.1 | F6: Report SVB’s Texas Ratio (from Q9) and your RAROC result (from Q10), including the
A7: Loans to Individuals | B7: 0.71 | C7: 14.78 | D7: =B7-C7 -> -14.07 | F7: benchmark. What do these metrics suggest about the importance of credit risk in SVB’s
A8: Non-Depository and Other | B8: 56.17 | C8: 18.84 | D8: =B8-C8 -> 37.33 | F8: overall risk profile? Was credit risk the primary driver of SVB’s failure? If not, explain briefly
A9: Foreign Office Loans & Leases | B9: 10.03 | C9: 2.68 | D9: =B9-C9 -> 7.35 | F9: what role, if any, credit risk played
A11: Q8. CREDIT QUALITY METRICS
A12: Metric | B12: SVB | C12: Peer Group 1 | D12: Difference
A13: Net Loss to Avg Total LN&LS (%) | B13: 0.1 | C13: 0.24 | D13: =B13-C13 -> -0.14
A14: ACL on LN&LS HFI to LN&LS HFI (%) | B14: 0.86 | C14: 1.24 | D14: =B14-C14 -> -0.38
A15: ACL on LN&LS HFI to Nonaccrual LN&LS (X) | B15: 4.78 | C15: 3.49 | D15: =B15-C15 -> 1.29
A16: Earnings Coverage of Net Losses (X) | B16: 42.15 | C16: 103.38 | D16: =B16-C16 -> -61.23
A17: Non-Curr Lns+OREO to Lns+OREO (%) | B17: 0.19 | C17: 0.61 | D17: =B17-C17 -> -0.42
A18: 30-89 Days Past Due (%) | B18: 0.14 | C18: 0.49 | D18: =B18-C18 -> -0.35
A19: Total LN&LS 90+ Days PD & Nonaccrual (%) | B19: 0.19 | C19: 0.6 | D19: =B19-C19 -> -0.41
A21: Q9. TEXAS RATIO
A22: Compute SVB's Texas Ratio:
A23: Texas Ratio = (Non-Current Loans + OREO) / (Tangible Common Equity + ACL on LN&LS) × 100
A24: where Tangible Common Equity = Total Bank Equity Capital - Total Intangibles.
A25: Item | B25: Value ($000s)
A26: Non-Current LN&LS ($000s) | B26: ='Data Extraction'!B96 -> 139000
A27: Other Real Estate Owned ($000s) | B27: ='Data Extraction'!B12 -> 0
A28: Numerator: Non-Current + OREO ($000s) | B28: =B26+B27 -> 139000
A29: Total Bank Capital & Min Int ($000s) | B29: ='Data Extraction'!B25 -> 15456000
A30: Total Intangibles ($000s) | B30: ='Data Extraction'!B29 -> 285000
A31: Tangible Common Equity ($000s) | B31: =B29-B30 -> 15171000
A32: ACL on LN&LS HFI ($000s) | B32: ='Data Extraction'!B7 -> 636000
A33: Denominator: TCE + ACL ($000s) | B33: =B31+B32 -> 15807000
A34: Texas Ratio (%) | B34: =B28/B33*100 -> 0.87935725
A36: Q10. RAROC CALCULATION
A37: Compute RAROC for SVB's Commercial & Industrial loan portfolio:
A38: RAROC = One-Year Net Income on Loan / Capital at Risk × 100
A39: where:
A40: One-Year Net Income = Loan × (Yield + Commitment Fee - Cost of Funds)
A41: Capital at Risk (ΔLN) = Duration × Loan × ΔR / (1+R)
A42: ΔR is the maximum adverse change in the risk premium. Compare RAROC to the benchmark (Cost of Funds + 275 bps).
A43: Parameter | B43: Value
A44: Commercial Loan Amount ($000s) | B44: ='Data Extraction'!B6 -> 19094000
A45: Market Interest Rate: C&I Yield (%) | B45: ='Data Extraction'!B46 -> 6.66
A46: Annual Commitment Fee (decimal) | B46: 0.0045
A47: Loan Duration (years) | B47: 5.984
A48: Cost of Funds: All Int-Bearing Funds (%) | B48: ='Data Extraction'!B49 -> 0.6
A49: Max Adverse Change in Risk Premium (%) | B49: 2.98
A50: One-Year Net Income ($000s) | B50: =B44*(B45/100+B46-B48/100) -> 1243019.4
A51: ΔLN = Capital at Risk ($000s) | B51: =B47*B44*(B49/100)/(1+B48/100) -> 3384595.6
A52: RAROC (%) | B52: =B50/B51*100 -> 36.725788
A53: Benchmark (%) | B53: =B48+2.75 -> 3.35
A54: Decision: Accept or Reject? | B54: Accept | C54: Compare RAROC to Benchmark

Sheet Capital Adequacy
A1: PART 2D: CAPITAL ADEQUACY ANALYSIS
A3: Q11. REGULATORY CAPITAL RATIOS
A4: Determine SVB's PCA category. "Well Capitalized" requires: CET1≥6.5%, Tier1≥8%, Total≥10%, Leverage≥5%.
A6: Capital Ratio | B6: Value | C6: Well-Capitalized Minimum | D6: SVB Meets? (Yes/No)
A7: CET1 Capital Ratio (%) | B7: ='Data Extraction'!B101 -> 15.2639 | C7: 0.065 | D7: Yes
A8: Tier 1 Capital Ratio (%) | B8: ='Data Extraction'!B102 -> 15.26 | C8: 0.08 | D8: Yes
A9: Total Capital Ratio (%) | B9: ='Data Extraction'!B103 -> 16.0507 | C9: 0.1 | D9: Yes
A10: Leverage Ratio (%) | B10: ='Data Extraction'!B100 -> 7.9626 | C10: 0.05 | D10: Yes
A12: Overall PCA Category: | B12: Well-Capitalized | C12: Well Cap. / Adequately Cap. / Undercapitalized / etc.
A14: Q12. RISK-WEIGHTED ASSETS COMPOSITION
A15: Compute each risk-weight category as a percentage of Total RWA.
A16: RWA Category | B16: RWA Value ($000s) | C16: % of Total RWA
A17: 20% Category (On-BS) | B17: ='Data Extraction'!B106 -> 15750200 | C17: =B17/$B$24*100 -> 14.145912
A18: 50% Category (On-BS) | B18: ='Data Extraction'!B107 -> 4666500 | C18: =B18/$B$24*100 -> 4.1911785
A19: 100% Category (On-BS) | B19: ='Data Extraction'!B108 -> 68948000 | C19: =B19/$B$24*100 -> 61.925077
A20: 150% Category (On-BS) | B20: ='Data Extraction'!B109 -> 10500 | C20: =B20/$B$24*100 -> 0.0094304883
A21: Other On-BS Categories | B21: ='Data Extraction'!B110 -> 23000 | C21: =B21/$B$24*100 -> 0.02065726
A22: On-Balance Sheet RWA Subtotal | B22: ='Data Extraction'!B111 -> 89598200 | C22: =B22/$B$24*100 -> 80.471884
A23: Derivatives, Off-BS and Other Risk Weight | B23: ='Data Extraction'!B112 -> 21741500 | C23: =B23/$B$24*100 -> 19.526949
A24: Total Risk-Weighted Assets | B24: ='Data Extraction'!B113 -> 111341000 | C24: =B24/$B$24*100 -> 100

Sheet Stress Scenario
A1: PART 3: STRESS SCENARIO ANALYSIS
A3: SCENARIO PARAMETERS
A5: Scenario | B5: Interest Rate Shock | C5: NPL Increase (pp) | D5: Deposit Outflow (%)
A6: A | B6: 0.015 | C6: 2 | D6: 40
A7: B | B7: 0.02 | C7: 1.5 | D7: 42
A8: C | B8: 0.025 | C8: 3 | D8: 44
A9: D | B9: -0.01 | C9: 1 | D9: 41
A10: E | B10: 0.03 | C10: 2.5 | D10: 46
A11: F | B11: 0.01 | C11: 4 | D11: 45
A12: G | B12: 0.02 | C12: 3.5 | D12: 50
A13: H | B13: 0.015 | C13: 0.5 | D13: 43
A15: YOUR ASSIGNED SCENARIO: | B15: F | C15: Enter A-H
A17: Q13. STRESS - INTEREST RATE RISK
A18: Calculate the stressed NII using your 1-Year Cumulative GAP from Q1.
A19: Step | B19: Value
A20: 1. Cumulative 1-Year GAP ($000s) [from Q1] | B20: ='Interest Rate Risk'!G9 -> -1.0246455e+08
A21: 2. Interest Rate Shock from your scenario | B21: =VLOOKUP($B$15, $A$6:$D$13, 2, FALSE) -> 0.01
A22: 3. ΔNII ($000s) | B22: =B20*B21 -> -1024645.5
A23: 4. Baseline Net Interest Income ($000s) [from Data Extr.] | B23: ='Data Extraction'!B37 -> 4611646
A24: 5. Stressed NII ($000s) | B24: =B23+B22 -> 3587000.5
A25: 6. % Change in NII | B25: =B22/B23*100 -> -22.218649
A27: Q14. STRESS - CREDIT RISK
A28: Apply the NPL increase from your assigned scenario to SVB's loan portfolio. Assume a Loss Given Default (LGD) of 45% on new non-performing loans. Compute the additional provisions required and the stressed ACL.
A29: Step | B29: Value
A30: 1. Baseline Non-Curr Lns+OREO to Lns+OREO (%) [from Data Extr.] | B30: ='Data Extraction'!B93 -> 0.19
A31: 2. NPL Increase from scenario (pp) | B31: =VLOOKUP($B$15, $A$6:$D$13, 3, FALSE) -> 4
A32: 3. Stressed NPL Ratio (%) | B32: =B31+B30 -> 4.19
A33: 4. Total Loans + OREO ($000s) [≈ Net Loans + ACL + OREO] | B33: ='Data Extraction'!B5+'Data Extraction'!B7+'Data Extraction'!B12 -> 74249000
A34: 5. New Non-Performing Loans ($000s) = NPL increase pp × Total Loans | B34: =B31/100*B33 -> 2969960
A35: 6. Loss Given Default (LGD) in % | B35: 45
A36: 7. Additional Provisions = New NPLs × LGD ($000s) | B36: =B34/100*B35 -> 1336482
A37: 8. Baseline ACL [from Data Extr.] | B37: ='Data Extraction'!B7 -> 636000
A38: 9. Stressed ACL ($000s) | B38: =B36+B37 -> 1972482
A40: Q15. STRESS - LIQUIDITY RISK
A41: Compute the deposit outflow from your assigned scenario. Assume outflow comes entirely from uninsured deposits.
A42: Compare the scenario deposit outflow to SVB’s cash-like assets and determine whether the bank faces a liquidity shortfall.
A43: Step | B43: Value
A44: 1. Estimate of Uninsured Deposits ($000s) [from Q5] | B44: ='Liquidity Risk'!B17 -> 151592000
A45: 2. Deposit Outflow % from scenario | B45: =VLOOKUP($B$15, $A$6:$D$13, 4, FALSE) -> 45
A46: 3. Deposits Lost ($000s) | B46: =B44*B45/100 -> 68216400
A47: 4. Cash-like Assets in ($000s) [from Q6 calculation] | B47: ='Liquidity Risk'!B40 -> 13231346
A48: 5. Surplus / (Shortfall) | B48: =B47-B46 -> -54985054
A49: 6. Uninsured Deposits After Outflow ($000s) | B49: =B44-B46 -> 83375600
A50: 7. Can SVB meet the outflow from cash-like assets alone? (Yes/No) | B50: No
A52: Q16. STRESS - CAPITAL ADEQUACY
A53: Compute the stressed Tier 1 ratio, and Leverage ratio.
A54: Assume SVB first uses cash-like liquidity to absorb deposit outflows. Any remaining shortfall is met by
A55: selling AFS securities first and then HTM securities if necessary, realizing proportional shares of unrealized losses.
A56: Determine SVB's stressed PCA category.
A57: Step | B57: Value
A58: 1. Baseline Tier 1 Capital ($000s) [from Data Extraction] | B58: ='Data Extraction'!B105 -> 16995000
A59: 2. Additional Provisions Required ($000s) [from Q14] | B59: =B36 -> 1336482
A60: 3. Liquidity shortfall after using cash-like assets ($000s) [from Q15] | B60: =ABS(B48) -> 54985054 | C60: Stored this as a positive value
A61: 4. AFS Sec Fair Value $ ($000s) [from Q6] | B61: ='Liquidity Risk'!B37 -> 25981932
A62: 5. Amount of AFS sold ($000s) = lesser of shortfall and total AFS fair value | B62: =MIN(B60,B61) -> 25981932
A63: 6. Estimated $ Unrealized Loss on AFS Securities [from Q3] | B63: ='Interest Rate Risk'!B40 -> -2525457
A64: 7. Realized loss on AFS sales ($000s) = (AFS sold / total AFS fair value) × total unrealized AFS loss | B64: =ABS(B63)*(B62/B61) -> 2525457 | C64: Stored this as a positive value
A65: 8. Remaining shortfall after AFS sales ($000s) = initial shortfall - AFS sold | B65: =B60-B62 -> 29003122 | C65: Stored this as a positive value
A66: 9. HTM Securities Fair Value ($000s) [from Q6] | B66: ='Liquidity Risk'!B38 -> 76169074
A67: 10. Amount of HTM sold ($000s) = lesser of remaining shortfall and total HTM fair value | B67: =MIN(B66, B65) -> 29003122
A68: 11. Estimated $ Unrealized Loss on HTM Securities [from Q3] | B68: ='Interest Rate Risk'!B41 -> -15159540
A69: 12. Realized loss on HTM sales ($000s) = (HTM sold / total HTM fair value) × total unrealized HTM loss | B69: =ABS(B68)*B67/B66 -> 5772342.6 | C69: Stored this as a positive value
A70: 13. Total realized securities (AFS + HTM) losses ($000s) | B70: =B64+B69 -> 8297799.6
A71: 14. Stressed Tier 1 Capital = Baseline - Provisions - Realized Losses | B71: =B58-B59-B70 -> 7360718.4
A72: 15. Total RWA ($000s) [from Data Extraction] | B72: ='Data Extraction'!B113 -> 111341000
A73: 16. Stressed Tier 1 Ratio (%) = Stressed T1 / RWA | B73: =B71/B72*100 -> 6.6109685
A74: 17. Stressed Leverage Ratio (%) = Stressed T1 / Total Assets | B74: =B71/'Data Extraction'!B13*100 -> 3.5214368
A75: 18. PCA Category under stress | B75: Undercapitalized | C75: Well Cap. / Adequately Cap. / Undercapitalized / etc.

Sheet Peer Comparison
A1: PART 4: PEER COMPARISON
A3: Download your comparison bank's UBPR from https://cdr.ffiec.gov/public/ for 12/31/2022.
A5: Assigned Comparison Bank: | B5: The Bank of New York Mellon
A7: Q17. COMPARATIVE RISK METRICS
A9: Metric | B9: SVB | C9: Comparison Bank | D9: Difference
A10: Net Int Inc (TE) to Avg Earn Assets (%) | B10: ='Data Extraction'!B43 -> 2.2 | C10: 1 | D10: =B10-C10 -> 1.2
A11: Non-Curr Lns+OREO to Lns+OREO (%) | B11: ='Data Extraction'!B93 -> 0.19 | C11: 0.17 | D11: =B11-C11 -> 0.02
A12: Net Loans & Leases to Deposits (%) | B12: ='Data Extraction'!B69 -> 41.97 | C12: 11.15 | D12: =B12-C12 -> 30.82
A13: Non-retirement Dep > $250M to Total Assets (%) | B13: ='Data Extraction'!B76 -> 74.99 | C13: 56.63 | D13: =B13-C13 -> 18.36
A14: Long-Term Assets to Total Assets (%) | B14: ='Data Extraction'!B55 -> 51.92 | C14: 19.87 | D14: =B14-C14 -> 32.05
A15: AFS/HTM Unrl App (Dep) to Tier 1 Cap (%) | B15: ='Data Extraction'!B64 -> -104.06 | C15: -60.65 | D15: =B15-C15 -> -43.41
A16: Com Equity Tier 1 Cap Ratio (%) | B16: ='Data Extraction'!B101 -> 15.2639 | C16: 16.3161 | D16: =B16-C16 -> -1.0522
A17: Leverage Ratio (%) | B17: ='Data Extraction'!B100 -> 7.9626 | C17: 6.2455 | D17: =B17-C17 -> 1.7171
A20: COMPARISON BANK OPTIONS:
A21: JPMorgan Chase Bank (RSSD: 852218)
A22: Bank of America (RSSD: 480228)
A23: Wells Fargo Bank (RSSD: 451965)
A24: Citibank (RSSD: 476810)
A25: U.S. Bank (RSSD: 504713)
A26: PNC Bank (RSSD: 817824)
A27: Truist Bank (RSSD: 852320)
A28: Goldman Sachs Bank (RSSD: 2182786)
A29: Morgan Stanley Bank (RSSD: 1456501)
A30: The Bank of New York Mellon (RSSD: 541101)
